qunitsuite/__init__.py
qunitsuite/suite.py
qunitsuite/grunt/bootstrap.js
qunitsuite/grunt/license
qunitsuite/grunt/phantomjs.json
qunitsuite/grunt/qunit-phantomjs-bridge.js
qunitsuite/tests/__init__.py
qunitsuite/tests/test_errors.py
qunitsuite/tests/test_reporting.py
qunitsuite/tests/utils.py
QUnitSuite-0.4.dist-info/LICENSE
QUnitSuite-0.4.dist-info/METADATA
QUnitSuite-0.4.dist-info/WHEEL
QUnitSuite-0.4.dist-info/top_level.txt
QUnitSuite-0.4.dist-info/RECORD
