Metadata-Version: 2.1
Name: QUnitSuite
Version: 0.4
Summary: unittest TestSuite integrating a QUnit javascript suite into a unittest flow
Author: Xavier Morel
Author-email: xavier.morel@masklinn.net
License: UNKNOWN
Platform: UNKNOWN
Classifier: Development Status :: 3 - Alpha
Classifier: Intended Audience :: Developers
Classifier: License :: OSI Approved :: BSD License
Classifier: Operating System :: OS Independent
Classifier: Programming Language :: Python
Classifier: Programming Language :: JavaScript
Classifier: Topic :: Software Development :: Testing
License-File: LICENSE
